onnxruntime_tools/__init__.py
onnxruntime_tools/optimizer_cli.py
onnxruntime_tools/symbolic_shape_infer.py
onnxruntime_tools/quantization/__init__.py
onnxruntime_tools/quantization/calibrate.py
onnxruntime_tools/quantization/data_preprocess.py
onnxruntime_tools/quantization/onnx_model.py
onnxruntime_tools/quantization/onnx_quantizer.py
onnxruntime_tools/quantization/qdq_quantizer.py
onnxruntime_tools/quantization/quant_utils.py
onnxruntime_tools/quantization/quantize.py
onnxruntime_tools/quantization/registry.py
onnxruntime_tools/quantization/CalTableFlatBuffers/KeyValue.py
onnxruntime_tools/quantization/CalTableFlatBuffers/TrtTable.py
onnxruntime_tools/quantization/CalTableFlatBuffers/__init__.py
onnxruntime_tools/quantization/operators/__init__.py
onnxruntime_tools/quantization/operators/activation.py
onnxruntime_tools/quantization/operators/attention.py
onnxruntime_tools/quantization/operators/base_operator.py
onnxruntime_tools/quantization/operators/binary_op.py
onnxruntime_tools/quantization/operators/conv.py
onnxruntime_tools/quantization/operators/embed_layernorm.py
onnxruntime_tools/quantization/operators/gather.py
onnxruntime_tools/quantization/operators/gavgpool.py
onnxruntime_tools/quantization/operators/lstm.py
onnxruntime_tools/quantization/operators/matmul.py
onnxruntime_tools/quantization/operators/maxpool.py
onnxruntime_tools/quantization/operators/pad.py
onnxruntime_tools/quantization/operators/qdq_base_operator.py
onnxruntime_tools/quantization/operators/reshape.py
onnxruntime_tools/quantization/operators/split.py
onnxruntime_tools/transformers/BertOnnxModel.py
onnxruntime_tools/transformers/BertOnnxModelKeras.py
onnxruntime_tools/transformers/BertOnnxModelTF.py
onnxruntime_tools/transformers/Gpt2OnnxModel.py
onnxruntime_tools/transformers/MachineInfo.py
onnxruntime_tools/transformers/OnnxModel.py
onnxruntime_tools/transformers/ShapeOptimizer.py
onnxruntime_tools/transformers/__init__.py
onnxruntime_tools/transformers/benchmark.py
onnxruntime_tools-1.7.0.dist-info/METADATA
onnxruntime_tools-1.7.0.dist-info/WHEEL
onnxruntime_tools-1.7.0.dist-info/top_level.txt
onnxruntime_tools-1.7.0.dist-info/RECORD
