Metadata-Version: 2.1
Name: onnxruntime-tools
Version: 1.7.0
Summary: Transformers Model Optimization Tool of ONNXRuntime
Home-page: https://github.com/microsoft/onnxruntime
Author: Microsoft Corporation
Author-email: onnx@microsoft.com
License: MIT License
Platform: UNKNOWN
Classifier: Development Status :: 4 - Beta
Classifier: Environment :: Console
Classifier: Intended Audience :: Developers
Classifier: Operating System :: POSIX
Classifier: Operating System :: Microsoft :: Windows
Classifier: Programming Language :: Python :: 3 :: Only
Classifier: Programming Language :: Python :: 3.5
Classifier: Programming Language :: Python :: 3.6
Classifier: Programming Language :: Python :: 3.7
Classifier: Programming Language :: Python :: 3.8
Classifier: License :: OSI Approved :: MIT License
